.editorconfig
AUTHORS.rst
CHANGES.md
CONTRIBUTING.rst
INSTALL.rst
LICENSE
MANIFEST.in
Makefile
README.md
pytest.ini
run-tests.sh
setup.cfg
setup.py
docs/Makefile
docs/api.rst
docs/authors.rst
docs/changes.rst
docs/conf.py
docs/configuration.rst
docs/contributing.rst
docs/index.rst
docs/installation.rst
docs/license.rst
docs/make.bat
docs/requirements.txt
docs/usage.rst
invenio_subjects_gnd/__init__.py
invenio_subjects_gnd/cli.py
invenio_subjects_gnd/converter.py
invenio_subjects_gnd/reader.py
invenio_subjects_gnd/version.py
invenio_subjects_gnd/writer.py
invenio_subjects_gnd.egg-info/PKG-INFO
invenio_subjects_gnd.egg-info/SOURCES.txt
invenio_subjects_gnd.egg-info/dependency_links.txt
invenio_subjects_gnd.egg-info/entry_points.txt
invenio_subjects_gnd.egg-info/not-zip-safe
invenio_subjects_gnd.egg-info/requires.txt
invenio_subjects_gnd.egg-info/top_level.txt
invenio_subjects_gnd/download/__init__.py
invenio_subjects_gnd/download/download.py
invenio_subjects_gnd/vocabularies/__init__.py
invenio_subjects_gnd/vocabularies/subjects_gnd.yaml
invenio_subjects_gnd/vocabularies/vocabularies.yaml
tests/conftest.py
tests/test_invenio_subjects_gnd.py