Metadata-Version: 2.1
Name: invenio-subjects-gnd
Version: 2022.2.1
Summary: GND subject terms for InvenioRDM
Home-page: https://github.com/ulbmuenster/invenio-subjects-gnd
Author: University of Münster
Author-email: werner.gresshoff@uni-muenster.de
License: MIT
Keywords: invenio inveniordm subjects GND
Platform: any
Classifier: Environment :: Web Environment
Classifier: Intended Audience :: Developers
Classifier: License :: OSI Approved :: MIT License
Classifier: Operating System :: OS Independent
Classifier: Programming Language :: Python
Classifier: Topic :: Internet :: WWW/HTTP :: Dynamic Content
Classifier: Topic :: Software Development :: Libraries :: Python Modules
Classifier: Programming Language :: Python :: 3
Classifier: Programming Language :: Python :: 3.6
Classifier: Programming Language :: Python :: 3.7
Classifier: Programming Language :: Python :: 3.8
Classifier: Programming Language :: Python :: 3.9
Provides-Extra: docs
Provides-Extra: tests
Provides-Extra: dev
Provides-Extra: all
License-File: LICENSE
License-File: AUTHORS.rst
